lazychef/__init__.py
lazychef/data_sources.py
lazychef/keras_generators.py
lazychef/lookup_tables.py
lazychef-0.0.2.dist-info/DESCRIPTION.rst
lazychef-0.0.2.dist-info/METADATA
lazychef-0.0.2.dist-info/RECORD
lazychef-0.0.2.dist-info/WHEEL
lazychef-0.0.2.dist-info/metadata.json
lazychef-0.0.2.dist-info/top_level.txt
