Metadata-Version: 2.0
Name: lazychef
Version: 0.0.2
Summary: Build machine pipelines that are lazily evaluated
Home-page: https://github.com/coopie/lazychef
Author: Sam Coope
Author-email: sam.j.coope@gmail.com
License: MIT
Download-URL: https://github.com/coopie/lazychef/archive/master.zip
Platform: UNKNOWN
Requires-Dist: h5py
Requires-Dist: numpy
